{
    "version": 2,
    "github": {
        "autoAlias": true
    },

    "builds": [
        {
            "ng": "ng",
            "start": "ng serve",
            "build": "ng build",
            "test": "ng test",
            "lint": "ng lint",
            "e2e": "ng e2e",
            "dev:ssr": "ng run angular.io-example:serve-ssr",
            "serve:ssr": "node dist/server/main.js",
            "build:ssr": "ng build --prod && ng run angular.io-example:server:production",
            "prerender": "ng run angular.io-example:prerender"
        }
    ]
    
}